holidaylist/__init__.py
holidaylist/holidays.py
holidaylist-0.4.dist-info/METADATA
holidaylist-0.4.dist-info/WHEEL
holidaylist-0.4.dist-info/top_level.txt
holidaylist-0.4.dist-info/RECORD
